Workbook

Sheet COVER PAGE
A2: Integrated Financial Model & DCF Valuation
A4: ITC Ltd.
A7: Project Objective
A8: To develop an integrated three-statement financial model for ITC Ltd.
A9: using historical financial data and estimate the company's intrinsic value through Discounted Cash Flow (DCF) valuation to support investment decision-making.
A12: Financial Period | J12: Tools & Techniques
A13: Historical Data: FY2021 – FY2025 | J13: Microsoft Excel
A14: Forecast Period: FY2026 – FY2032 | J14: Financial Statement Analysis
J15: Three-Statement Financial Modelling
J16: Financial Forecasting
A17: Model Components
A18: Assumptions
A19: Income Statement | J19: Key Deliverables
A20: Balance Sheet | J20: Historical Financial Analysis | N20: Free Cash Flow (FCF) Estimation
A21: Cash Flow Statement | J21: Forecasted Financial Statements | N21: Enterprise & Equity Valuation
A22: DCF Valuation | J22: Integrated Three-Statement Model | N22: Intrinsic Share Price Estimation

Sheet Assumptions
A3: Assumptions
A4: revenue growth % | C4: 0.08
A5: COGS % of Revenue | C5: 0.28
A6: Employee Expense % of Revenue | C6: 0.06
A7: Other Expense % of Revenue | C7: 0.15
A8: Depreciation % of Revenue | C8: 0.03
A9: Tax Rate % | C9: 0.2
A10: Capex % | C10: 0.05
A11: Change In Working Capital % | C11: 0.02
A12: WACC | C12: 0.1
A13: g | C13: 0.03
A14: Receivable Days | C14: ='Balance sheet'!I8/'Profit & loss'!I5*365 -> 21.107963
A15: Inventory Days | C15: ='Balance sheet'!I7/'Profit & loss'!I7*365 -> 240.25046
A16: Payable Days | C16: ='Balance sheet'!I16/'Profit & loss'!I7*365 -> 73.857816

Sheet Profit & loss
A1: ITC LIMITED
D2: FY 2020 | E2: FY 2021 | F2: FY 2022 | G2: FY 2023 | H2: FY 2024 | I2: FY 2025 | J2: FY 2026 | K2: FY 2027 | L2: FY 2028 | M2: FY 2029 | N2: FY 2030 | O2: FY 2031 | P2: FY 2032
A3: PROFIT & LOSS | D3: 43921 | E3: 44286 | F3: 44651 | G3: 45016 | H3: 45382 | I3: 45747 | J3: 46112 | K3: 46477 | L3: 46843 | M3: 47208 | N3: 47573 | O3: 47574 | P3: 47575
A5: Revenue | D5: 46807.34 | E5: 48524.54 | F5: 59745.56 | G5: 70251.28 | H5: 70105.29 | I5: 81612.78 | J5: =I5*(1+J6) -> 88141.802 | K5: =J5*(1+K6) -> 96074.565 | L5: =K5*(1+L6) -> 103760.53 | M5: =L5*(1+M6) -> 112061.37 | N5: =M5*(1+N6) -> 121026.28 | O5: =N5*(1+O6) -> 130708.38 | P5: =O5*(1+P6) -> 141165.06
A6: Revenue Growth % | E6: =E5/D5-1 -> 0.036686554 | F6: =F5/E5-1 -> 0.23124423 | G6: =G5/F5-1 -> 0.17584102 | H6: =H5/G5-1 -> -0.0020781116 | I6: =I5/H5-1 -> 0.16414582 | J6: 0.08 | K6: 0.09 | L6: 0.08 | M6: 0.08 | N6: 0.08 | O6: 0.08 | P6: 0.08
A7: (-) COGS | D7: 13121.76 | E7: 13605.07 | F7: 16064.5 | G7: 19809.83 | H7: 21309.84 | I7: 23757.33 | J7: =J5*J8 -> 24679.705 | K7: =K5*K8 -> 26900.878 | L7: =L5*L8 -> 29052.948 | M7: =M5*M8 -> 31377.184 | N7: =N5*N8 -> 33887.359 | O7: =O5*O8 -> 36598.348 | P7: =P5*P8 -> 39526.215
A8: COGS % | D8: =D7/D5 -> 0.28033552 | E8: =E7/E5 -> 0.28037504 | F8: =F7/F5 -> 0.26888191 | G8: =G7/G5 -> 0.28198532 | H8: =H7/H5 -> 0.30396907 | I8: =I7/I5 -> 0.29109816 | J8: 0.28 | K8: 0.28 | L8: 0.28 | M8: 0.28 | N8: 0.28 | O8: 0.28 | P8: 0.28
A9: Gross Profit | D9: =D5-D7 -> 33685.58 | E9: =E5-E7 -> 34919.47 | F9: =F5-F7 -> 43681.06 | G9: =G5-G7 -> 50441.45 | H9: =H5-H7 -> 48795.45 | I9: =I5-I7 -> 57855.45 | J9: =J5-J7 -> 63462.098 | K9: =K5-K7 -> 69173.687 | ... P9: =P5-P7 -> 101638.84
A11: (-) Employee Expense | D11: 2658.21 | E11: 2820.95 | F11: 3061.99 | G11: 3569.46 | H11: 3732.23 | I11: 6169.78 | J11: =J5*J12 -> 5288.5081 | K11: =K5*K12 -> 5764.4739 | L11: =L5*L12 -> 6225.6318 | M11: =M5*M12 -> 6723.6823 | N11: =N5*N12 -> 7261.5769 | O11: =O5*O12 -> 7842.5031 | P11: =P5*P12 -> 8469.9033
A12: Employee Expense % | D12: =D11/D5 -> 0.056790452 | E12: =E11/E5 -> 0.058134503 | F12: =F11/F5 -> 0.051250503 | G12: =G11/G5 -> 0.050809893 | H12: =H11/H5 -> 0.053237495 | I12: =I11/I5 -> 0.075598209 | J12: 0.06 | K12: 0.06 | L12: 0.06 | M12: 0.06 | N12: 0.06 | O12: 0.06 | P12: 0.06
A13: (-) Other Expense | D13: 7822.11 | E13: 7167.09 | F13: 8113.1 | G13: 9649.16 | H13: 10247.87 | I13: 11196.63 | J13: =J5*J14 -> 13221.27 | K13: =K5*K14 -> 14411.185 | L13: =L5*L14 -> 15564.079 | M13: =M5*M14 -> 16809.206 | N13: =N5*N14 -> 18153.942 | O13: =O5*O14 -> 19606.258 | P13: =P5*P14 -> 21174.758
A14: Other Expense % | D14: =D13/D5 -> 0.16711289 | E14: =E13/E5 -> 0.14770032 | F14: =F13/F5 -> 0.13579419 | G14: =G13/G5 -> 0.13735209 | H14: =H13/H5 -> 0.14617827 | I14: =I13/I5 -> 0.13719212 | J14: 0.15 | K14: 0.15 | L14: 0.15 | M14: 0.15 | N14: 0.15 | O14: 0.15 | P14: 0.15
A15: EBITDA | D15: =D9-D11-D13 -> 23205.26 | E15: =E9-E11-E13 -> 24931.43 | F15: =F9-F11-F13 -> 32505.97 | G15: =G9-G11-G13 -> 37222.83 | H15: =H9-H11-H13 -> 34815.35 | I15: =I9-I11-I13 -> 40489.04 | J15: =J9-J11-J13 -> 44952.319 | K15: =K9-K11-K13 -> 48998.028 | ... P15: =P9-P11-P13 -> 71994.178
A16: EBITDA Margin % | D16: =D15/D5 -> 0.49576113 | E16: =E15/E5 -> 0.51379014 | F16: =F15/F5 -> 0.5440734 | G16: =G15/G5 -> 0.52985269 | H16: =H15/H5 -> 0.49661516 | I16: =I15/I5 -> 0.49611152 | J16: =J15/J5 -> 0.51 | K16: =K15/K5 -> 0.51 | ... P16: =P15/P5 -> 0.51
A18: (-) Depreciation | D18: 1563.27 | E18: 1561.83 | F18: 1652.15 | G18: 1662.73 | H18: 1647.82 | I18: 1646.32 | J18: =J5*J19 -> 1762.836 | K18: =K5*K19 -> 1921.4913 | L18: =L5*L19 -> 2075.2106 | M18: =M5*M19 -> 2241.2274 | N18: =N5*N19 -> 2420.5256 | O18: =O5*O19 -> 2614.1677 | P18: =P5*P19 -> 2823.3011
A19: Depreciation % | D19: =D18/D5 -> 0.033397967 | E19: =E18/E5 -> 0.032186395 | F19: =F18/F5 -> 0.027653101 | G19: =G18/G5 -> 0.023668323 | H19: =H18/H5 -> 0.023504931 | I19: =I18/I5 -> 0.020172331 | J19: 0.02 | K19: 0.02 | L19: 0.02 | M19: 0.02 | N19: 0.02 | O19: 0.02 | P19: 0.02
A20: EBIT | D20: =D15-D18 -> 21641.99 | E20: =E15-E18 -> 23369.6 | F20: =F15-F18 -> 30853.82 | G20: =G15-G18 -> 35560.1 | H20: =H15-H18 -> 33167.53 | I20: =I15-I18 -> 38842.72 | J20: =J15-J18 -> 43189.483 | K20: =K15-K18 -> 47076.537 | ... P20: =P15-P18 -> 69170.877
A21: EBIT Margin % | D21: =D20/D5 -> 0.46236317 | E21: =E20/E5 -> 0.48160374 | F21: =F20/F5 -> 0.5164203 | G21: =G20/G5 -> 0.50618437 | H21: =H20/H5 -> 0.47311023 | I21: =I20/I5 -> 0.47593919 | J21: =J20/J5 -> 0.49 | K21: =K20/K5 -> 0.49 | ... P21: =P20/P5 -> 0.49
A23: (-) Tax | D23: =4441.97+(411.21) -> 4853.18 | E23: =4035.36+97.15 -> 4132.51 | F23: =4833.88+(62.18) -> 4896.06 | G23: =6025.32+(28.22) -> 6053.54 | H23: =5661.21+232.59 -> 5893.8 | I23: =6509.61+380.86 -> 6890.47 | J23: =J20*J24 -> 8637.8966 | K23: =K20*K24 -> 9415.3073 | L23: =L20*L24 -> 10168.532 | M23: =M20*M24 -> 10982.014 | N23: =N20*N24 -> 11860.576 | O23: =O20*O24 -> 12809.422 | P23: =P20*P24 -> 13834.175
A24: Tax Margin % | D24: =D23/D20 -> 0.22424832 | E24: =E23/E20 -> 0.17683272 | F24: =F23/F20 -> 0.1586857 | G24: =G23/G20 -> 0.17023405 | H24: =H23/H20 -> 0.17769789 | I24: =I23/I20 -> 0.17739412 | J24: 0.2 | K24: 0.2 | L24: 0.2 | M24: 0.2 | N24: 0.2 | O24: 0.2 | P24: 0.2
A25: PAT (Net Income) | D25: =D20-D23 -> 16788.81 | E25: =E20-E23 -> 19237.09 | F25: =F20-F23 -> 25957.76 | G25: =G20-G23 -> 29506.56 | H25: =H20-H23 -> 27273.73 | I25: =I20-I23 -> 31952.25 | J25: =J20-J23 -> 34551.587 | K25: =K20-K23 -> 37661.229 | ... P25: =P20-P23 -> 55336.702
A26: PAT Margin % | D26: =D25/D5 -> 0.358679 | E26: =E25/E5 -> 0.39644044 | F26: =F25/F5 -> 0.43447178 | G26: =G25/G5 -> 0.42001455 | H26: =H25/H5 -> 0.38903954 | I26: =I25/I5 -> 0.39151037 | J26: =J25/J5 -> 0.392 | K26: =K25/K5 -> 0.392 | ... P26: =P25/P5 -> 0.392

Sheet Cash flow statement
D2: FY 2020 | E2: FY 2021 | F2: FY 2022 | G2: FY 2023 | H2: FY 2024 | I2: FY 2025 | J2: FY 2026 | K2: FY 2027 | L2: FY 2028 | M2: FY 2029 | N2: FY 2030 | O2: FY 2031 | P2: FY 2032
A3: CASH FLOW | D3: 43921 | E3: 44286 | F3: 44651 | G3: 45016 | H3: 45382 | I3: 45747 | J3: 46112 | K3: 46477 | L3: 46843 | M3: 47208 | N3: 47573 | O3: 47574 | P3: 47575
A5: Opening Cash
A7: PAT (Net Income) | D7: ='Profit & loss'!D25 -> 16788.81 | E7: ='Profit & loss'!E25 -> 19237.09 | F7: ='Profit & loss'!F25 -> 25957.76 | G7: ='Profit & loss'!G25 -> 29506.56 | H7: ='Profit & loss'!H25 -> 27273.73 | I7: ='Profit & loss'!I25 -> 31952.25 | J7: ='Profit & loss'!J25 -> 34551.587 | K7: ='Profit & loss'!K25 -> 37661.229 | ... P7: ='Profit & loss'!P25 -> 55336.702
A8: (+) Depreciation | D8: ='Profit & loss'!D18 -> 1563.27 | E8: ='Profit & loss'!E18 -> 1561.83 | F8: ='Profit & loss'!F18 -> 1652.15 | G8: ='Profit & loss'!G18 -> 1662.73 | H8: ='Profit & loss'!H18 -> 1647.82 | I8: ='Profit & loss'!I18 -> 1646.32 | J8: ='Profit & loss'!J18 -> 1762.836 | K8: ='Profit & loss'!K18 -> 1921.4913 | ... P8: ='Profit & loss'!P18 -> 2823.3011
A9: – Change in Working Capital | E9: ='Balance sheet'!E27 -> 758.36 | F9: ='Balance sheet'!F27 -> 285.18 | G9: ='Balance sheet'!G27 -> 837.1 | H9: ='Balance sheet'!H27 -> 2889.44 | I9: ='Balance sheet'!I27 -> 4096.52 | J9: ='Balance sheet'!J27 -> 798.05677 | K9: ='Balance sheet'!K27 -> 1471.3188 | L9: ='Balance sheet'!L27 -> 1425.5444 | ... P9: ='Balance sheet'!P27 -> 2531.8921
A10: – Capex | D10: ='Balance sheet'!D6 -> 18932.57 | E10: ='Balance sheet'!E6 -> 18489.91 | F10: ='Balance sheet'!F6 -> 19559.15 | G10: ='Balance sheet'!G6 -> 20491.32 | H10: ='Balance sheet'!H6 -> 22015.5 | I10: ='Balance sheet'!I6 -> 17428.89 | J10: ='Profit & loss'!J5*Assumptions!C10 -> 4407.0901 | K10: ='Profit & loss'!K5*Assumptions!C10 -> 4803.7282 | L10: ='Profit & loss'!L5*Assumptions!C10 -> 5188.0265 | M10: ='Profit & loss'!M5*Assumptions!C10 -> 5603.0686 | N10: ='Profit & loss'!N5*Assumptions!C10 -> 6051.3141 | O10: ='Profit & loss'!O5*Assumptions!C10 -> 6535.4192 | P10: ='Profit & loss'!P5*Assumptions!C10 -> 7058.2528
A12: Free Cash Flow | D12: =D7+D8-D9-D10 -> -580.49 | E12: =E7+E8-E9-E10 -> 1550.65 | F12: =F7+F8-F9-F10 -> 7765.58 | G12: =G7+G8-G9-G10 -> 9840.87 | H12: =H7+H8-H9-H10 -> 4016.61 | I12: =I7+I8-I9-I10 -> 12073.16 | J12: =J7+J8-J9-J10 -> 31109.276 | K12: =K7+K8-K9-K10 -> 33307.674 | ... P12: =P7+P8-P9-P10 -> 48569.858
A14: (+) Opening Cash | D14: 162.75 | E14: 561.35 | F14: 231.28 | G14: 184.98 | H14: 405.91 | I14: 596.58 | J14: =I15 -> 622.38 | K14: =J15 -> 31731.656 | L14: =K15 -> 65039.329 | M14: =L15 -> 101175.1 | N14: =M15 -> 140201.73 | O14: =N15 -> 182350.48 | P14: =O15 -> 220465.46
A15: Closing Cash | D15: 561.35 | E15: 231.25 | F15: 184.98 | G15: 206.88 | H15: 596.58 | I15: 622.38 | J15: =J12+J14 -> 31731.656 | K15: =K12+K14 -> 65039.329 | L15: =L12+L14 -> 101175.1 | M15: =M12+M14 -> 140201.73 | N15: =N12+N14 -> 182350.48 | O15: =O12+O14 -> 220465.46 | P15: =P12+P14 -> 269035.32

Sheet Balance sheet
D2: FY 2020 | E2: FY 2021 | F2: FY 2022 | G2: FY 2023 | H2: FY 2024 | I2: FY 2025 | J2: FY 2026 | K2: FY 2027 | L2: FY 2028 | M2: FY 2029 | N2: FY 2030 | O2: FY 2031 | P2: FY 2032
A3: BALANCE SHEET | D3: 43921 | E3: 44286 | F3: 44651 | G3: 45016 | H3: 45382 | I3: 45747 | J3: 46112 | K3: 46477 | L3: 46843 | M3: 47208 | N3: 47573 | O3: 47574 | P3: 47575
A5: Assets
A6: PPE | D6: 18932.57 | E6: 18489.91 | F6: 19559.15 | G6: 20491.32 | H6: 22015.5 | I6: 17428.89
A7: Inventory | D7: 8038.07 | E7: 9470.87 | F7: 9997.77 | G7: 10593.9 | H7: 12631.51 | I7: 15637.56 | J7: ='Profit & loss'!J7*Assumptions!C15/365 -> 16244.686 | K7: ='Profit & loss'!K7*Assumptions!C15/365 -> 17706.708 | L7: ='Profit & loss'!L7*Assumptions!C15/365 -> 19123.244 | M7: ='Profit & loss'!M7*Assumptions!C15/365 -> 20653.104 | N7: ='Profit & loss'!N7*Assumptions!C15/365 -> 22305.352 | O7: ='Profit & loss'!O7*Assumptions!C15/365 -> 24089.78 | P7: ='Profit & loss'!P7*Assumptions!C15/365 -> 26016.963
A8: Receivables | D8: 2092 | E8: 2090.35 | F8: 1952.5 | G8: 2321.33 | H8: 3311.45 | I8: 4719.67 | J8: ='Profit & loss'!J5*Assumptions!C14/365 -> 5097.2436 | K8: ='Profit & loss'!K5*Assumptions!C14/365 -> 5555.9955 | L8: ='Profit & loss'!L5*Assumptions!C14/365 -> 6000.4752 | M8: ='Profit & loss'!M5*Assumptions!C14/365 -> 6480.5132 | N8: ='Profit & loss'!N5*Assumptions!C14/365 -> 6998.9542 | O8: ='Profit & loss'!O5*Assumptions!C14/365 -> 7558.8706 | P8: ='Profit & loss'!P5*Assumptions!C14/365 -> 8163.5802
A9: Other Current + Non-current Assets | D9: =847.74+1364.71 -> 2212.45 | E9: =1231.62+1006.07 -> 2237.69 | F9: =1228.92+1195.15 -> 2424.07 | G9: =1211.74+1388.09 -> 2599.83 | H9: =1229.22+1134.18 -> 2363.4 | I9: =1015.93+1371.85 -> 2387.78 | J9: ='Profit & loss'!J5*'Balance sheet'!J10 -> 3525.6721 | K9: ='Profit & loss'!K5*'Balance sheet'!K10 -> 3842.9826 | L9: ='Profit & loss'!L5*'Balance sheet'!L10 -> 4150.4212 | M9: ='Profit & loss'!M5*'Balance sheet'!M10 -> 4482.4549 | N9: ='Profit & loss'!N5*'Balance sheet'!N10 -> 4841.0513 | O9: ='Profit & loss'!O5*'Balance sheet'!O10 -> 5228.3354 | P9: ='Profit & loss'!P5*'Balance sheet'!P10 -> 5646.6022
A10: Other Current + Non-current Assets % | D10: =D9/'Profit & loss'!D5 -> 0.047267159 | E10: =E9/'Profit & loss'!E5 -> 0.046114605 | F10: =F9/'Profit & loss'!F5 -> 0.040573224 | G10: =G9/'Profit & loss'!G5 -> 0.037007582 | H10: =H9/'Profit & loss'!H5 -> 0.033712149 | I10: =I9/'Profit & loss'!I5 -> 0.029257428 | J10: 0.04 | K10: 0.04 | L10: 0.04 | M10: 0.04 | N10: 0.04 | O10: 0.04 | P10: 0.04
A11: Cash | D11: 561.84 | E11: 231.25 | F11: 184.97 | G11: 206.88 | H11: 197.63 | I11: 620 | J11: =I11+'Cash flow statement'!J10 -> 5027.0901 | K11: =J11+'Cash flow statement'!K10 -> 9830.8184 | L11: =K11+'Cash flow statement'!L10 -> 15018.845 | M11: =L11+'Cash flow statement'!M10 -> 20621.913 | N11: =M11+'Cash flow statement'!N10 -> 26673.228 | O11: =N11+'Cash flow statement'!O10 -> 33208.647 | P11: =O11+'Cash flow statement'!P10 -> 40266.9
A12: Total Assets | D12: =D6+D7+D8+D9+D11 -> 31836.93 | E12: =E6+E7+E8+E9+E11 -> 32520.07 | F12: =F6+F7+F8+F9+F11 -> 34118.46 | G12: =G6+G7+G8+G9+G11 -> 36213.26 | H12: =H6+H7+H8+H9+H11 -> 40519.49 | I12: =I6+I7+I8+I9+I11 -> 40793.9 | J12: =J7+J8+J9+J11 -> 29894.692 | K12: =K7+K8+K9+K11 -> 36936.504 | L12: =L7+L8+L9+L11 -> 44292.985 | M12: =M7+M8+M9+M11 -> 52237.985 | N12: =N7+N8+N9+N11 -> 60818.585 | O12: =O7+O8+O9+O11 -> 70085.633 | P12: =P7+P8+P9+P11 -> 80094.045
A14: Liabilities
A15: Debt (Borrowings + Lease) | D15: =5.63+259.25+64.87 -> 329.75 | E15: =5.28+272.36+51.36 -> 329 | F15: =4.54+259.79+0.74+46.09 -> 311.16 | G15: =3.28+273.59+1.26+46.54 -> 324.67 | H15: =1.76+261.95+1.52+46.74 -> 311.97 | I15: =137.21+91.26+56.07 -> 284.54 | J15: 284.54 | K15: 284.54 | L15: 284.54 | M15: 284.54 | N15: 284.54 | O15: 284.54 | P15: 284.54
A16: Payables | D16: =34.67+3412.07 -> 3446.74 | E16: =59.34+4060.19 -> 4119.53 | F16: =100.96+4122.44 -> 4223.4 | G16: =137.5+4213.76 -> 4351.26 | H16: =206.85+4282.7 -> 4489.55 | I16: =180.64+4626.66 -> 4807.3 | J16: ='Profit & loss'!J7*Assumptions!C16/365 -> 4993.9427 | K16: ='Profit & loss'!K7*Assumptions!C16/365 -> 5443.3975 | L16: ='Profit & loss'!L7*Assumptions!C16/365 -> 5878.8693 | M16: ='Profit & loss'!M7*Assumptions!C16/365 -> 6349.1789 | N16: ='Profit & loss'!N7*Assumptions!C16/365 -> 6857.1132 | O16: ='Profit & loss'!O7*Assumptions!D16/365 -> 0 | P16: ='Profit & loss'!P7*Assumptions!E16/365 -> 0
A17: Other Liabilities | D17: =90.47+1147.24 -> 1237.71 | E17: =239.35+4369 -> 4608.35 | F17: =96.5+5097.28 -> 5193.78 | G17: =152.49+5446.16 -> 5598.65 | H17: =149.72+5594.72 -> 5744.44 | I17: =34.51+6148.27 -> 6182.78 | J17: ='Profit & loss'!J5*'Balance sheet'!J18 -> 6169.9262 | K17: ='Profit & loss'!K5*'Balance sheet'!K18 -> 6725.2195 | L17: ='Profit & loss'!L5*'Balance sheet'!L18 -> 7263.2371 | M17: ='Profit & loss'!M5*'Balance sheet'!M18 -> 7844.2961 | N17: ='Profit & loss'!N5*'Balance sheet'!N18 -> 8471.8397 | O17: ='Profit & loss'!O5*'Balance sheet'!O18 -> 9149.5869 | P17: ='Profit & loss'!P5*'Balance sheet'!P18 -> 9881.5539
A18: Other Liabilities % | D18: =D17/'Profit & loss'!D5 -> 0.026442648 | E18: =E17/'Profit & loss'!E5 -> 0.094969473 | F18: =F17/'Profit & loss'!F5 -> 0.086931648 | G18: =G17/'Profit & loss'!G5 -> 0.079694633 | H18: =H17/'Profit & loss'!H5 -> 0.081940179 | I18: =I17/'Profit & loss'!I5 -> 0.075757498 | J18: 0.07 | K18: 0.07 | L18: 0.07 | M18: 0.07 | N18: 0.07 | O18: 0.07 | P18: 0.07
A19: Total Liabilities | D19: =SUM(D15:D17) -> 5014.2 | E19: =SUM(E15:E17) -> 9056.88 | F19: =SUM(F15:F17) -> 9728.34 | G19: =SUM(G15:G17) -> 10274.58 | H19: =SUM(H15:H17) -> 10545.96 | I19: =SUM(I15:I17) -> 11274.62 | J19: =SUM(J15:J17) -> 11448.409 | K19: =SUM(K15:K17) -> 12453.157 | ... P19: =SUM(P15:P17) -> 10166.094
A21: Equity
A22: Share Capital (constant) | D22: 1229.22 | E22: 1230.88 | F22: 1232.33 | G22: 1242.8 | H22: 1248.47 | I22: 1251.41 | J22: 1251.41 | K22: 1251.41 | L22: 1251.41 | M22: 1251.41 | N22: 1251.41 | O22: 1251.41 | P22: 1251.41
A23: Retained Earnings | D23: 62799.94 | E23: 57773.7 | F23: 60167.24 | G23: 66351 | H23: 70984.83 | I23: 68778.64 | J23: =I23+'Profit & loss'!J25 -> 103330.23 | K23: =J23+'Profit & loss'!K25 -> 140991.46 | L23: =K23+'Profit & loss'!L25 -> 181665.58 | M23: =L23+'Profit & loss'!M25 -> 225593.64 | N23: =M23+'Profit & loss'!N25 -> 273035.94 | O23: =N23+'Profit & loss'!O25 -> 324273.63 | P23: =O23+'Profit & loss'!P25 -> 379610.33
A24: Total Equity | D24: =SUM(D22:D23) -> 64029.16 | E24: =SUM(E22:E23) -> 59004.58 | F24: =SUM(F22:F23) -> 61399.57 | G24: =SUM(G22:G23) -> 67593.8 | H24: =SUM(H22:H23) -> 72233.3 | I24: =SUM(I22:I23) -> 70030.05 | J24: =J22+J23 -> 104581.64 | K24: =K22+K23 -> 142242.87 | L24: =L22+L23 -> 182916.99 | M24: =M22+M23 -> 226845.05 | N24: =N22+N23 -> 274287.35 | O24: =O22+O23 -> 325525.04 | P24: =P22+P23 -> 380861.74
A26: Working Capital | D26: =D7+D8-D16 -> 6683.33 | E26: =E7+E8-E16 -> 7441.69 | F26: =F7+F8-F16 -> 7726.87 | G26: =G7+G8-G16 -> 8563.97 | H26: =H7+H8-H16 -> 11453.41 | I26: =I7+I8-I16 -> 15549.93 | J26: =J7+J8-J16 -> 16347.987 | K26: =K7+K8-K16 -> 17819.306 | ... P26: =P7+P8-P16 -> 34180.543
A27: Change in Working Cpital | E27: =E26-D26 -> 758.36 | F27: =F26-E26 -> 285.18 | G27: =G26-F26 -> 837.1 | H27: =H26-G26 -> 2889.44 | I27: =I26-H26 -> 4096.52 | J27: =J26-I26 -> 798.05677 | K27: =K26-J26 -> 1471.3188 | L27: =L26-K26 -> 1425.5444 | ... P27: =P26-O26 -> 2531.8921

Sheet DCF Valuation
C2: FY 2026 | D2: FY 2027 | E2: FY 2028 | F2: FY 2029 | G2: FY 2030 | H2: FY 2031 | I2: FY 2032
A3: DCF VALUATION | C3: 46112 | D3: 46477 | E3: 46843 | F3: 47208 | G3: 47573 | H3: 47574 | I3: 47575
A5: FCF | C5: ='Cash flow statement'!J12 -> 31109.276 | D5: ='Cash flow statement'!K12 -> 33307.674 | E5: ='Cash flow statement'!L12 -> 36135.767 | F5: ='Cash flow statement'!M12 -> 39026.629 | G5: ='Cash flow statement'!N12 -> 42148.759 | H5: ='Cash flow statement'!O12 -> 38114.978 | I5: ='Cash flow statement'!P12 -> 48569.858
A7: DISCOUNT FACTOR | C7: =1/(1+Assumptions!C12)^1 -> 0.90909091 | D7: =1/(1+Assumptions!C12)^2 -> 0.82644628 | E7: =1/(1+Assumptions!C12)^3 -> 0.7513148 | F7: =1/(1+Assumptions!C12)^4 -> 0.68301346 | G7: =1/(1+Assumptions!C12)^5 -> 0.62092132 | H7: =1/(1+Assumptions!D12)^5 -> 1 | I7: =1/(1+Assumptions!E12)^5 -> 1
A8: PV OF FCF | C8: =C5*C7 -> 28281.16 | D8: =D5*D7 -> 27527.003 | E8: =E5*E7 -> 27149.337 | F8: =F5*F7 -> 26655.713 | G8: =G5*G7 -> 26171.063 | H8: =H5*H7 -> 38114.978 | I8: =I5*I7 -> 48569.858
A9: TERMINAL VALUE (TV) | I9: ='Cash flow statement'!P12*(1+Assumptions!C13)/(Assumptions!C12-Assumptions!C13) -> 714670.77
A11: PV OF TV | I11: =I9*I7 -> 714670.77
A13: ENTERPRISE VALUE (EV) | I13: =I5/(1+Assumptions!C12)^5+I9/(1+Assumptions!C12)^5 -> 473912.38
A15: EQUITY VALUE | I15: =I13+('Balance sheet'!P11-'Balance sheet'!P15) -> 513894.74
A17: SHARE PRICE | I17: =I15/1251.41 -> 410.65257
